{
  "currentTime": "03/04/2018 06:24 PM",
  "stamp": "03/04/2018 06:24 PM",
  "tourCode": "R",
  "md5Sum": "7a9ce5e9468d3741c9c6f97f06145254",
  "player": {
    "lastName": "Hatton",
    "country": "ENG",
    "currentRound": 4,
    "firstName": "Tyrrell",
    "id": "34363",
    "status": "T3",
    "stats": {
      "stat": []
    },
    "round": [
      {
        "courseCode": "240",
        "courseName": "240",
        "startingHole": 1,
        "roundNum": 4,
        "hole": [
          {
            "par": 4,
            "score": "3",
            "yard": 316,
            "videoUrl": "",
            "id": "1",
            "videoFlag": 0,
            "totalParRelative": "-12"
          },
          {
            "par": 4,
            "score": "3",
            "yard": 387,
            "videoUrl": "",
            "id": "2",
            "videoFlag": 0,
            "totalParRelative": "-13"
          },
          {
            "par": 3,
            "score": "3",
            "yard": 186,
            "videoUrl": "",
            "id": "3",
            "videoFlag": 0,
            "totalParRelative": "-13"
          },
          {
            "par": 4,
            "score": "3",
            "yard": 506,
            "videoUrl": "",
            "id": "4",
            "videoFlag": 0,
            "totalParRelative": "-14"
          },
          {
            "par": 4,
            "score": "4",
            "yard": 445,
            "videoUrl": "",
            "id": "5",
            "videoFlag": 0,
            "totalParRelative": "-14"
          },
          {
            "par": 5,
            "score": "6",
            "yard": 625,
            "videoUrl": "",
            "id": "6",
            "videoFlag": 0,
            "totalParRelative": "-13"
          },
          {
            "par": 3,
            "score": "3",
            "yard": 235,
            "videoUrl": "",
            "id": "7",
            "videoFlag": 0,
            "totalParRelative": "-13"
          },
          {
            "par": 4,
            "score": "4",
            "yard": 525,
            "videoUrl": "",
            "id": "8",
            "videoFlag": 0,
            "totalParRelative": "-13"
          },
          {
            "par": 4,
            "score": "4",
            "yard": 382,
            "videoUrl": "",
            "id": "9",
            "videoFlag": 0,
            "totalParRelative": "-13"
          },
          {
            "par": 35,
            "score": "33",
            "yard": 3607,
            "videoUrl": "",
            "id": "OUT",
            "videoFlag": 0,
            "totalParRelative": ""
          },
          {
            "par": 4,
            "score": "4",
            "yard": 450,
            "videoUrl": "",
            "id": "10",
            "videoFlag": 0,
            "totalParRelative": "-13"
          },
          {
            "par": 5,
            "score": "6",
            "yard": 622,
            "videoUrl": "",
            "id": "11",
            "videoFlag": 0,
            "totalParRelative": "-12"
          },
          {
            "par": 4,
            "score": "3",
            "yard": 406,
            "videoUrl": "",
            "id": "12",
            "videoFlag": 0,
            "totalParRelative": "-13"
          },
          {
            "par": 3,
            "score": "3",
            "yard": 225,
            "videoUrl": "",
            "id": "13",
            "videoFlag": 0,
            "totalParRelative": "-13"
          },
          {
            "par": 4,
            "score": "3",
            "yard": 497,
            "videoUrl": "",
            "id": "14",
            "videoFlag": 0,
            "totalParRelative": "-14"
          },
          {
            "par": 5,
            "score": "3",
            "yard": 575,
            "videoUrl": "",
            "id": "15",
            "videoFlag": 0,
            "totalParRelative": "-16"
          },
          {
            "par": 4,
            "score": "4",
            "yard": 403,
            "videoUrl": "",
            "id": "16",
            "videoFlag": 0,
            "totalParRelative": "-16"
          },
          {
            "par": 3,
            "score": "3",
            "yard": 172,
            "videoUrl": "",
            "id": "17",
            "videoFlag": 0,
            "totalParRelative": "-16"
          },
          {
            "par": 4,
            "score": "",
            "yard": 388,
            "videoUrl": "",
            "id": "18",
            "videoFlag": 0,
            "totalParRelative": " "
          },
          {
            "par": 36,
            "score": "",
            "yard": 3738,
            "videoUrl": "",
            "id": "IN",
            "videoFlag": 0,
            "totalParRelative": ""
          },
          {
            "par": 71,
            "score": "",
            "yard": 7345,
            "videoUrl": "",
            "id": "TOTAL",
            "videoFlag": 0,
            "totalParRelative": ""
          }
        ],
        "partner": [
          "01810",
          "39113"
        ]
      },
      {
        "courseCode": "240",
        "courseName": "240",
        "startingHole": 1,
        "roundNum": 3,
        "hole": [
          {
            "par": 4,
            "score": "3",
            "yard": 316,
            "videoUrl": "",
            "id": "1",
            "videoFlag": 0,
            "totalParRelative": "-5"
          },
          {
            "par": 4,
            "score": "3",
            "yard": 387,
            "videoUrl": "",
            "id": "2",
            "videoFlag": 0,
            "totalParRelative": "-6"
          },
          {
            "par": 3,
            "score": "3",
            "yard": 186,
            "videoUrl": "",
            "id": "3",
            "videoFlag": 0,
            "totalParRelative": "-6"
          },
          {
            "par": 4,
            "score": "4",
            "yard": 506,
            "videoUrl": "",
            "id": "4",
            "videoFlag": 0,
            "totalParRelative": "-6"
          },
          {
            "par": 4,
            "score": "3",
            "yard": 445,
            "videoUrl": "",
            "id": "5",
            "videoFlag": 0,
            "totalParRelative": "-7"
          },
          {
            "par": 5,
            "score": "5",
            "yard": 625,
            "videoUrl": "",
            "id": "6",
            "videoFlag": 0,
            "totalParRelative": "-7"
          },
          {
            "par": 3,
            "score": "3",
            "yard": 235,
            "videoUrl": "",
            "id": "7",
            "videoFlag": 0,
            "totalParRelative": "-7"
          },
          {
            "par": 4,
            "score": "3",
            "yard": 525,
            "videoUrl": "",
            "id": "8",
            "videoFlag": 0,
            "totalParRelative": "-8"
          },
          {
            "par": 4,
            "score": "3",
            "yard": 382,
            "videoUrl": "",
            "id": "9",
            "videoFlag": 0,
            "totalParRelative": "-9"
          },
          {
            "par": 35,
            "score": "30",
            "yard": 3607,
            "videoUrl": "",
            "id": "OUT",
            "videoFlag": 0,
            "totalParRelative": ""
          },
          {
            "par": 4,
            "score": "4",
            "yard": 450,
            "videoUrl": "",
            "id": "10",
            "videoFlag": 0,
            "totalParRelative": "-9"
          },
          {
            "par": 5,
            "score": "5",
            "yard": 622,
            "videoUrl": "",
            "id": "11",
            "videoFlag": 0,
            "totalParRelative": "-9"
          },
          {
            "par": 4,
            "score": "3",
            "yard": 406,
            "videoUrl": "",
            "id": "12",
            "videoFlag": 0,
            "totalParRelative": "-10"
          },
          {
            "par": 3,
            "score": "3",
            "yard": 225,
            "videoUrl": "",
            "id": "13",
            "videoFlag": 0,
            "totalParRelative": "-10"
          },
          {
            "par": 4,
            "score": "4",
            "yard": 497,
            "videoUrl": "",
            "id": "14",
            "videoFlag": 0,
            "totalParRelative": "-10"
          },
          {
            "par": 5,
            "score": "4",
            "yard": 575,
            "videoUrl": "",
            "id": "15",
            "videoFlag": 0,
            "totalParRelative": "-11"
          },
          {
            "par": 4,
            "score": "4",
            "yard": 403,
            "videoUrl": "",
            "id": "16",
            "videoFlag": 0,
            "totalParRelative": "-11"
          },
          {
            "par": 3,
            "score": "3",
            "yard": 172,
            "videoUrl": "",
            "id": "17",
            "videoFlag": 0,
            "totalParRelative": "-11"
          },
          {
            "par": 4,
            "score": "4",
            "yard": 388,
            "videoUrl": "",
            "id": "18",
            "videoFlag": 0,
            "totalParRelative": "-11"
          },
          {
            "par": 36,
            "score": "34",
            "yard": 3738,
            "videoUrl": "",
            "id": "IN",
            "videoFlag": 0,
            "totalParRelative": ""
          },
          {
            "par": 71,
            "score": "64",
            "yard": 7345,
            "videoUrl": "",
            "id": "TOTAL",
            "videoFlag": 0,
            "totalParRelative": ""
          }
        ],
        "partner": [
          "27064",
          "34098"
        ]
      },
      {
        "courseCode": "240",
        "courseName": "240",
        "startingHole": 10,
        "roundNum": 2,
        "hole": [
          {
            "par": 4,
            "score": "4",
            "yard": 316,
            "videoUrl": "",
            "id": "1",
            "videoFlag": 0,
            "totalParRelative": "-2"
          },
          {
            "par": 4,
            "score": "3",
            "yard": 387,
            "videoUrl": "",
            "id": "2",
            "videoFlag": 0,
            "totalParRelative": "-3"
          },
          {
            "par": 3,
            "score": "3",
            "yard": 186,
            "videoUrl": "",
            "id": "3",
            "videoFlag": 0,
            "totalParRelative": "-3"
          },
          {
            "par": 4,
            "score": "4",
            "yard": 506,
            "videoUrl": "",
            "id": "4",
            "videoFlag": 0,
            "totalParRelative": "-3"
          },
          {
            "par": 4,
            "score": "4",
            "yard": 445,
            "videoUrl": "",
            "id": "5",
            "videoFlag": 0,
            "totalParRelative": "-3"
          },
          {
            "par": 5,
            "score": "5",
            "yard": 625,
            "videoUrl": "",
            "id": "6",
            "videoFlag": 0,
            "totalParRelative": "-3"
          },
          {
            "par": 3,
            "score": "2",
            "yard": 235,
            "videoUrl": "",
            "id": "7",
            "videoFlag": 0,
            "totalParRelative": "-4"
          },
          {
            "par": 4,
            "score": "4",
            "yard": 525,
            "videoUrl": "",
            "id": "8",
            "videoFlag": 0,
            "totalParRelative": "-4"
          },
          {
            "par": 4,
            "score": "4",
            "yard": 382,
            "videoUrl": "",
            "id": "9",
            "videoFlag": 0,
            "totalParRelative": "-4"
          },
          {
            "par": 35,
            "score": "33",
            "yard": 3607,
            "videoUrl": "",
            "id": "OUT",
            "videoFlag": 0,
            "totalParRelative": ""
          },
          {
            "par": 4,
            "score": "4",
            "yard": 450,
            "videoUrl": "",
            "id": "10",
            "videoFlag": 0,
            "totalParRelative": "-1"
          },
          {
            "par": 5,
            "score": "5",
            "yard": 622,
            "videoUrl": "",
            "id": "11",
            "videoFlag": 0,
            "totalParRelative": "-1"
          },
          {
            "par": 4,
            "score": "4",
            "yard": 406,
            "videoUrl": "",
            "id": "12",
            "videoFlag": 0,
            "totalParRelative": "-1"
          },
          {
            "par": 3,
            "score": "3",
            "yard": 225,
            "videoUrl": "",
            "id": "13",
            "videoFlag": 0,
            "totalParRelative": "-1"
          },
          {
            "par": 4,
            "score": "4",
            "yard": 497,
            "videoUrl": "",
            "id": "14",
            "videoFlag": 0,
            "totalParRelative": "-1"
          },
          {
            "par": 5,
            "score": "4",
            "yard": 575,
            "videoUrl": "",
            "id": "15",
            "videoFlag": 0,
            "totalParRelative": "-2"
          },
          {
            "par": 4,
            "score": "4",
            "yard": 403,
            "videoUrl": "",
            "id": "16",
            "videoFlag": 0,
            "totalParRelative": "-2"
          },
          {
            "par": 3,
            "score": "3",
            "yard": 172,
            "videoUrl": "",
            "id": "17",
            "videoFlag": 0,
            "totalParRelative": "-2"
          },
          {
            "par": 4,
            "score": "4",
            "yard": 388,
            "videoUrl": "",
            "id": "18",
            "videoFlag": 0,
            "totalParRelative": "-2"
          },
          {
            "par": 36,
            "score": "35",
            "yard": 3738,
            "videoUrl": "",
            "id": "IN",
            "videoFlag": 0,
            "totalParRelative": ""
          },
          {
            "par": 71,
            "score": "68",
            "yard": 7345,
            "videoUrl": "",
            "id": "TOTAL",
            "videoFlag": 0,
            "totalParRelative": ""
          }
        ],
        "partner": [
          "25364",
          "26851"
        ]
      },
      {
        "courseCode": "240",
        "courseName": "240",
        "startingHole": 1,
        "roundNum": 1,
        "hole": [
          {
            "par": 4,
            "score": "3",
            "yard": 316,
            "videoUrl": "",
            "id": "1",
            "videoFlag": 0,
            "totalParRelative": "-1"
          },
          {
            "par": 4,
            "score": "5",
            "yard": 387,
            "videoUrl": "",
            "id": "2",
            "videoFlag": 0,
            "totalParRelative": "E"
          },
          {
            "par": 3,
            "score": "3",
            "yard": 186,
            "videoUrl": "",
            "id": "3",
            "videoFlag": 0,
            "totalParRelative": "E"
          },
          {
            "par": 4,
            "score": "4",
            "yard": 506,
            "videoUrl": "",
            "id": "4",
            "videoFlag": 0,
            "totalParRelative": "E"
          },
          {
            "par": 4,
            "score": "4",
            "yard": 445,
            "videoUrl": "",
            "id": "5",
            "videoFlag": 0,
            "totalParRelative": "E"
          },
          {
            "par": 5,
            "score": "5",
            "yard": 625,
            "videoUrl": "",
            "id": "6",
            "videoFlag": 0,
            "totalParRelative": "E"
          },
          {
            "par": 3,
            "score": "3",
            "yard": 235,
            "videoUrl": "",
            "id": "7",
            "videoFlag": 0,
            "totalParRelative": "E"
          },
          {
            "par": 4,
            "score": "4",
            "yard": 525,
            "videoUrl": "",
            "id": "8",
            "videoFlag": 0,
            "totalParRelative": "E"
          },
          {
            "par": 4,
            "score": "4",
            "yard": 382,
            "videoUrl": "",
            "id": "9",
            "videoFlag": 0,
            "totalParRelative": "E"
          },
          {
            "par": 35,
            "score": "35",
            "yard": 3607,
            "videoUrl": "",
            "id": "OUT",
            "videoFlag": 0,
            "totalParRelative": ""
          },
          {
            "par": 4,
            "score": "4",
            "yard": 450,
            "videoUrl": "",
            "id": "10",
            "videoFlag": 0,
            "totalParRelative": "E"
          },
          {
            "par": 5,
            "score": "4",
            "yard": 622,
            "videoUrl": "",
            "id": "11",
            "videoFlag": 0,
            "totalParRelative": "-1"
          },
          {
            "par": 4,
            "score": "5",
            "yard": 406,
            "videoUrl": "",
            "id": "12",
            "videoFlag": 0,
            "totalParRelative": "E"
          },
          {
            "par": 3,
            "score": "3",
            "yard": 225,
            "videoUrl": "",
            "id": "13",
            "videoFlag": 0,
            "totalParRelative": "E"
          },
          {
            "par": 4,
            "score": "4",
            "yard": 497,
            "videoUrl": "",
            "id": "14",
            "videoFlag": 0,
            "totalParRelative": "E"
          },
          {
            "par": 5,
            "score": "4",
            "yard": 575,
            "videoUrl": "",
            "id": "15",
            "videoFlag": 0,
            "totalParRelative": "-1"
          },
          {
            "par": 4,
            "score": "4",
            "yard": 403,
            "videoUrl": "",
            "id": "16",
            "videoFlag": 0,
            "totalParRelative": "-1"
          },
          {
            "par": 3,
            "score": "3",
            "yard": 172,
            "videoUrl": "",
            "id": "17",
            "videoFlag": 0,
            "totalParRelative": "-1"
          },
          {
            "par": 4,
            "score": "4",
            "yard": 388,
            "videoUrl": "",
            "id": "18",
            "videoFlag": 0,
            "totalParRelative": "-1"
          },
          {
            "par": 36,
            "score": "35",
            "yard": 3738,
            "videoUrl": "",
            "id": "IN",
            "videoFlag": 0,
            "totalParRelative": ""
          },
          {
            "par": 71,
            "score": "70",
            "yard": 7345,
            "videoUrl": "",
            "id": "TOTAL",
            "videoFlag": 0,
            "totalParRelative": ""
          }
        ],
        "partner": [
          "25364",
          "26851"
        ]
      }
    ]
  },
  "hole": []
}
